django_template_obfuscator/__init__.py
django_template_obfuscator/apps.py
django_template_obfuscator/models.py
django_template_obfuscator/tests.py
django_template_obfuscator/urls.py
django_template_obfuscator/views.py
django_template_obfuscator/static/css/django_template_obfuscator.css
django_template_obfuscator/static/js/django_template_obfuscator.js
django_template_obfuscator/templates/django_template_obfuscator/base.html
django_template_obfuscator/templatetags/__init__.py
django_template_obfuscator/templatetags/encoder.py
django_template_obfuscator/templatetags/obfuscator.py
django_template_obfuscator-0.1.5.dist-info/AUTHORS.rst
django_template_obfuscator-0.1.5.dist-info/LICENSE
django_template_obfuscator-0.1.5.dist-info/METADATA
django_template_obfuscator-0.1.5.dist-info/WHEEL
django_template_obfuscator-0.1.5.dist-info/top_level.txt
django_template_obfuscator-0.1.5.dist-info/RECORD
