Metadata-Version: 2.1
Name: django-template-obfuscator
Version: 0.1.5
Summary: Obfuscates desired content in a Django template in order to be difficult to scrape
Home-page: https://github.com/rafahuelin/django-template-obfuscator
Author: Rafa Huelin
Author-email: rafahuelin@gmail.com
License: MIT
Keywords: django-template-obfuscator
Platform: UNKNOWN
Classifier: Development Status :: 3 - Alpha
Classifier: Framework :: Django :: 1.11
Classifier: Framework :: Django :: 2.0
Classifier: Intended Audience :: Developers
Classifier: License :: OSI Approved :: BSD License
Classifier: Natural Language :: English
Classifier: Programming Language :: Python :: 2
Classifier: Programming Language :: Python :: 2.7
Classifier: Programming Language :: Python :: 3
Classifier: Programming Language :: Python :: 3.4
Classifier: Programming Language :: Python :: 3.5
Classifier: Programming Language :: Python :: 3.6
